winzy_macos_reminder/__init__.py
winzy_macos_reminder-0.0.3.dist-info/LICENSE
winzy_macos_reminder-0.0.3.dist-info/METADATA
winzy_macos_reminder-0.0.3.dist-info/WHEEL
winzy_macos_reminder-0.0.3.dist-info/entry_points.txt
winzy_macos_reminder-0.0.3.dist-info/top_level.txt
winzy_macos_reminder-0.0.3.dist-info/RECORD
