Metadata-Version: 2.1
Name: winzy-macos-reminder
Version: 0.0.3
Summary: Create reminers in macos in cli
Author: Sukhbinder Singh
License: Apache-2.0
Project-URL: Homepage, https://github.com/sukhbinder/winzy-macos-reminder
Project-URL: Changelog, https://github.com/sukhbinder/winzy-macos-reminder/releases
Project-URL: Issues, https://github.com/sukhbinder/winzy-macos-reminder/issues
Project-URL: CI, https://github.com/sukhbinder/winzy-macos-reminder/actions
Classifier: License :: OSI Approved :: Apache Software License
License-File: LICENSE
Requires-Dist: winzy
Requires-Dist: dateutils
Provides-Extra: test
Requires-Dist: pytest; extra == "test"
